MANIFEST.in
README.txt
diebang.py
setup.py
DieBang.egg-info/PKG-INFO
DieBang.egg-info/SOURCES.txt
DieBang.egg-info/dependency_links.txt
DieBang.egg-info/top_level.txt