Metadata-Version: 1.0
Name: DieBang
Version: 0.1
Summary: Remove inline comments denoted by '!' from files
Home-page: UNKNOWN
Author: Philip Schleihauf
Author-email: uniphil@gmail.com
License: GPLv3
Platform: UNKNOWN
